strands_robots/__init__.py
strands_robots/robot.py
strands_robots/policies/__init__.py
strands_robots/policies/groot/__init__.py
strands_robots/policies/groot/client.py
strands_robots/policies/groot/data_config.py
strands_robots/tools/__init__.py
strands_robots/tools/gr00t_inference.py
strands_robots/tools/lerobot_calibrate.py
strands_robots/tools/lerobot_camera.py
strands_robots/tools/lerobot_teleoperate.py
strands_robots/tools/pose_tool.py
strands_robots/tools/serial_tool.py
strands_robots-0.3.7.dist-info/licenses/LICENSE
strands_robots-0.3.7.dist-info/METADATA
strands_robots-0.3.7.dist-info/WHEEL
strands_robots-0.3.7.dist-info/top_level.txt
strands_robots-0.3.7.dist-info/RECORD
