Metadata-Version: 2.4
Name: strands-robots
Version: 0.3.7
Summary: Robot Control with LeRobot Integration for Strands Agents
Author-email: Cagatay Cali <cagataycali@icloud.com>
License: Apache-2.0
Project-URL: Homepage, https://github.com/cagataycali/strands-robots
Project-URL: Documentation, https://github.com/cagataycali/strands-robots#readme
Project-URL: Repository, https://github.com/cagataycali/strands-robots.git
Project-URL: Issues, https://github.com/cagataycali/strands-robots/issues
Keywords: robots,agents,lerobot,strands,sdk
Classifier: Development Status :: 4 - Beta
Classifier: Intended Audience :: Developers
Classifier: License :: OSI Approved :: Apache Software License
Classifier: Operating System :: OS Independent
Classifier: Programming Language :: Python :: 3
Classifier: Programming Language :: Python :: 3.10
Classifier: Programming Language :: Python :: 3.11
Classifier: Programming Language :: Python :: 3.12
Classifier: Topic :: Scientific/Engineering :: Artificial Intelligence
Classifier: Topic :: Software Development :: Libraries :: Python Modules
Requires-Python: >=3.10
License-File: LICENSE
Requires-Dist: strands-agents
Requires-Dist: lerobot
Requires-Dist: lerobot[feetech]
Requires-Dist: numpy>=1.21.0
Requires-Dist: torch>=2.0.0
Requires-Dist: opencv-python-headless>=4.5.0
Requires-Dist: Pillow>=8.0.0
Requires-Dist: msgpack>=1.0.0
Requires-Dist: pyzmq>=27.0.0
Provides-Extra: dev
Requires-Dist: pytest>=6.0; extra == "dev"
Requires-Dist: pytest-cov; extra == "dev"
Requires-Dist: black; extra == "dev"
Requires-Dist: isort; extra == "dev"
Requires-Dist: flake8; extra == "dev"
Requires-Dist: mypy; extra == "dev"
Dynamic: license-file
